parquetexplorer/__init__.py
parquetexplorer/data_table.py
parquetexplorer/grid.tcss
parquetexplorer/utils/__init__.py
parquetexplorer/utils/config.py
parquetexplorer/utils/logger.py
parquetexplorer-0.1.0.dist-info/LICENSE
parquetexplorer-0.1.0.dist-info/METADATA
parquetexplorer-0.1.0.dist-info/WHEEL
parquetexplorer-0.1.0.dist-info/RECORD
